hierarchical_conf/__init__.py
hierarchical_conf/hierarchical_conf.py
hierarchical_conf-1.0.4.dist-info/METADATA
hierarchical_conf-1.0.4.dist-info/WHEEL
hierarchical_conf-1.0.4.dist-info/top_level.txt
hierarchical_conf-1.0.4.dist-info/RECORD
