Metadata-Version: 2.1
Name: hierarchical-conf
Version: 1.0.4
Summary: A tool for loading settings from files hierarchically
Home-page: https://github.com/quintoandar/hierarchical-conf
Author: QuintoAndar
License: UNKNOWN
Keywords: hierarchical-conf,configuration by environment,configuration files,configuration as code,hierarchical configuration
Platform: UNKNOWN
Classifier: Natural Language :: English
Classifier: Programming Language :: Python :: 3
Classifier: Programming Language :: Python :: 3.7
Classifier: Programming Language :: Python :: 3.8
Requires-Python: >=3.7, <4
Requires-Dist: PyYAML (<=6.0.2,>=5.1)
